mahaNLP/__init__.py
mahaNLP/config.py
mahaNLP/autocomplete/__init__.py
mahaNLP/autocomplete/autocomplete.py
mahaNLP/datasets/__init__.py
mahaNLP/datasets/load_data.py
mahaNLP/hate/__init__.py
mahaNLP/hate/hate.py
mahaNLP/mask_fill/__init__.py
mahaNLP/mask_fill/mask_fill.py
mahaNLP/model_repo/__init__.py
mahaNLP/model_repo/maha_fill.py
mahaNLP/model_repo/maha_gpt.py
mahaNLP/model_repo/maha_hate.py
mahaNLP/model_repo/maha_ner.py
mahaNLP/model_repo/maha_sentiment.py
mahaNLP/model_repo/maha_similarity.py
mahaNLP/preprocess/__init__.py
mahaNLP/preprocess/marathi_stopwords.txt
mahaNLP/preprocess/preprocess.py
mahaNLP/sentiment/__init__.py
mahaNLP/sentiment/sentiment.py
mahaNLP/similarity/__init__.py
mahaNLP/similarity/similarity.py
mahaNLP/tagger/__init__.py
mahaNLP/tagger/tagger.py
mahaNLP/tokenizer/__init__.py
mahaNLP/tokenizer/tokenize.py
mahaNLP-0.9.dist-info/LICENSE
mahaNLP-0.9.dist-info/METADATA
mahaNLP-0.9.dist-info/WHEEL
mahaNLP-0.9.dist-info/top_level.txt
mahaNLP-0.9.dist-info/RECORD
