Metadata-Version: 2.1
Name: mahaNLP
Version: 0.9
Summary: An NLP Library for Marathi Language
Home-page: https://github.com/l3cube-pune/MarathiNLP.git
Author: L3Cube
Author-email: ravirajoshi@gmail.com
License: MIT
Classifier: Programming Language :: Python :: 3
Classifier: License :: OSI Approved :: MIT License
Classifier: Operating System :: OS Independent
License-File: LICENSE
Requires-Dist: importlib-resources
Requires-Dist: huggingface-hub (==0.11.1)
Requires-Dist: tqdm
Requires-Dist: pandas
Requires-Dist: sentence-transformers
Requires-Dist: transformers
Requires-Dist: numpy
Requires-Dist: torch
Requires-Dist: IPython
